PropositionTable/__init__.py
PropositionTable/proposition_table.py
PropositionTable-0.0.4rc2.dist-info/METADATA
PropositionTable-0.0.4rc2.dist-info/RECORD
PropositionTable-0.0.4rc2.dist-info/WHEEL
PropositionTable-0.0.4rc2.dist-info/entry_points.txt
PropositionTable-0.0.4rc2.dist-info/top_level.txt
