Metadata-Version: 2.1
Name: PropositionTable
Version: 0.0.4rc2
Summary: Draw table of all possible values of a propsition
Home-page: https://github.com/Dragneel1234/PropositionTable
Author: Dragneel1234
Author-email: blwal7057@gmail.com
License: GPL-3.0
Platform: UNKNOWN
Classifier: Development Status :: 4 - Beta
Classifier: Programming Language :: Python :: 3 :: Only
